sprite_splitter/__init__.py
sprite_splitter/box.py
sprite_splitter/edge_finder.py
sprite_splitter/sprite_splitter.py
sprite_splitter-0.0.4.dist-info/METADATA
sprite_splitter-0.0.4.dist-info/WHEEL
sprite_splitter-0.0.4.dist-info/top_level.txt
sprite_splitter-0.0.4.dist-info/RECORD
