Metadata-Version: 2.2
Name: sprite-splitter
Version: 0.0.4
Summary: A sprite image splitter for rgba format image.
Author: Binimation
License: MIT License
Project-URL: Homepage, https://github.com/Intro1997/SpriteSplitter
Classifier: Programming Language :: Python :: 3
Classifier: Operating System :: OS Independent
Requires-Python: >=3.12
Requires-Dist: Pillow~=10.4.0
